itsa/__init__.py
itsa/itsa_launcher.py
itsa/param_itsa.py
itsa/tsanalysis_itsa.py
itsa/gts/Gts.py
itsa/gts/errors.py
itsa/gts/lib/analysis.py
itsa/gts/lib/outliers.py
itsa/gts/lib/format/F3pos.py
itsa/gts/lib/format/GMODfiles.py
itsa/gts/lib/format/GXpos.py
itsa/gts/lib/format/NGLtxyz.py
itsa/gts/lib/format/PBOpos.py
itsa/gts/lib/format/read_pos.py
itsa/gts/lib/frame/euler_pole.py
itsa/gts/lib/frame/fixed_plate.py
itsa/gts/lib/frame/itrf_convert.py
itsa/gts/lib/primitive/check_gts.py
itsa/gts/lib/primitive/coordinates.py
itsa/gts/lib/primitive/copy.py
itsa/gts/lib/primitive/plot.py
itsa/gts/lib/primitive/select.py
itsa/gts/lib/primitive/time.py
itsa/gts/lib/primitive/velocity.py
itsa/jps/Jps.py
itsa/jps/errors.py
itsa/jps/lib/check_jps.py
itsa/jps/lib/copy.py
itsa/jps/lib/fill_jps.py
itsa/jps/lib/select.py
itsa/jps/lib/write_jps.py
itsa/lib/Glinalg.py
itsa/lib/Green_functions.py
itsa/lib/astrotime.py
itsa/lib/coordinates.py
itsa/lib/euler.py
itsa/lib/find_format.py
itsa/lib/index_dates.py
itsa/lib/log2staDB.py
itsa/lib/modif_vartype.py
itsa/lib/read_cat.py
itsa/lib/save_Gts_byproduct.py
itsa/lib/select_ev.py
itsa/utilities/__init__.py
itsa/utilities/convert_NGL2PBO.py
itsa/utilities/make_byproduct_itsa.py
itsa/utilities/remove_outliers.py
testitsa-0.0.1.dist-info/licenses/LICENSE.txt
testitsa-0.0.1.dist-info/METADATA
testitsa-0.0.1.dist-info/WHEEL
testitsa-0.0.1.dist-info/top_level.txt
testitsa-0.0.1.dist-info/RECORD
