Metadata-Version: 2.4
Name: TESTITSA
Version: 0.0.1
Summary: ISTerre Time Series Analysis (ITSA) is a tool developed by Lou Marill.  This tool, developed in Python, produces a trajectory model for GNSS time series.
Author: Lou Marill
Author-email: Anne SOCQUET <anne.socquet@univ-grenoble-alpes.fr>
Maintainer-email: Gaël JANEX <gael.janex@univ-grenoble-alpes.fr>, Oliver HENRIOT <Oliver.Henriot@univ-grenoble-alpes.fr>, Aubin TSAPONG TSAGUE <tsaponga@univ-grenoble-alpes.fr>
Project-URL: Documentation, https://gricad-gitlab.univ-grenoble-alpes.fr/isterre-cycle/itsa/-/wikis/home
Project-URL: Repository, https://gricad-gitlab.univ-grenoble-alpes.fr/isterre-cycle/itsa
Project-URL: Issues, https://gricad-gitlab.univ-grenoble-alpes.fr/isterre-cycle/itsa/-/issues
Keywords: gnss,gps,Time Series,Analysis,trajectory model
Classifier: Development Status :: 4 - Beta
Classifier: Intended Audience :: Science/Research
Classifier: Topic :: Scientific/Engineering :: Information Analysis
Classifier: Programming Language :: Python :: 3
Classifier: Programming Language :: Python :: 3.8
Classifier: Programming Language :: Python :: 3.9
Classifier: Operating System :: OS Independent
Requires-Python: >=3.7
License-File: LICENSE.txt
Requires-Dist: matplotlib==3.8.2
Requires-Dist: scipy==1.12.0
Requires-Dist: pandas==2.2.0
Requires-Dist: pyarrow==16.1.0
Requires-Dist: numpy==1.26.4
Dynamic: license-file
